<?xml version="1.0" encoding="UTF-8"?><extraction><clueid>42699654</clueid><fullpath><![CDATA[https://s.weibo.com/weibo?q=%E5%9B%BD%E6%BD%AE&xsort=hot&suball=1&timescope=custom:2020-05-01:2020-05-31&Refer=g&page=34]]></fullpath><realpath><![CDATA[https://s.weibo.com/weibo?q=%E5%9B%BD%E6%BD%AE&xsort=hot&suball=1&timescope=custom:2020-05-01:2020-05-31&Refer=g&page=34]]></realpath><theme>国潮下热门5月</theme><middle>规则_1</middle><createdate>2020-6-22 15:5:43</createdate><pageno>37</pageno><actionno></actionno><actionvalue></actionvalue><prestamp>DSEngine-+-ds_browser_sample-+-1592809508159</prestamp><currentstamp>DSEngine-+-ds_browser_sample-+-1592809543724</currentstamp><timestamp>1592809543724</timestamp><baseURI><bucketBaseURI><bucketName>讨论</bucketName><uri><![CDATA[https://s.weibo.com/weibo?q=%E5%9B%BD%E6%BD%AE&xsort=hot&suball=1&timescope=custom:2020-05-01:2020-05-31&Refer=g&page=34]]></uri></bucketBaseURI></baseURI><customInfo><![CDATA[]]></customInfo><dsName>DSEngine</dsName><dsThread>datascraper_sample</dsThread><version>80700</version>
<讨论><item><user>铁馆教练</user><内容>
                    如果平时我熟悉的品牌变成了我的室友会怎么样？跟我一起来看看吧！#中国潮中国造#  L铁馆教练的微博视频 ​                </内容><发布时间>
                        05月12日 12:45
                        </发布时间><来源>微博  weibo.com</来源><收藏>收藏</收藏><转发> 转发 2043</转发><评论>评论 921</评论><点赞数>1956</点赞数></item><item><user>景研竣</user><内容>
                    景研竣#国潮告白日# 走廊是个拍照的好地方！ ​                </内容><发布时间>
                        05月20日 18:02
                        </发布时间><来源>景研竣超话</来源><收藏>收藏</收藏><转发> 转发 2024</转发><评论>评论 2109</评论><点赞数>3253</点赞数></item><item><user>杨添小兄弟</user><内容>
                    #国潮告白日# 520你和谁在一起？拍照片时候我想笑，摄影师不让我笑，我问他为什么，他说单身汪你好意思笑嘛～所以，只能一脸莫得感情的亚子陪你们过节了～ ​                </内容><发布时间>
                        05月20日 16:15
                        </发布时间><来源>iPhone XS Max</来源><收藏>收藏</收藏><转发> 转发 384</转发><评论>评论 423</评论><点赞数>1057</点赞数></item><item><user>微博明星</user><内容>
                    #张艺兴新专辑先行曲玉#张艺兴@努力努力再努力x 第四张个人专辑先行曲《玉》今日上线，融合传统与流行，串联东方与西方，艺兴的音乐新鲜又动听，被“玉、玉、玉”洗脑了～#国潮PLUS挑战赛# ​                </内容><发布时间>
                        05月20日 00:15
                        </发布时间><来源>张艺兴超话</来源><收藏>收藏</收藏><转发> 转发 98</转发><评论>评论 80</评论><点赞数>425</点赞数></item><item><user>剧探王</user><内容>
                    #张予曦国潮旗袍# 张予曦穿旗袍韵味十足，最近热播的《韫色过浓》也是颜值爆表，谁看了不说绝！！ ​                </内容><发布时间>
                        05月10日 17:45
                        </发布时间><来源/><收藏>收藏</收藏><转发> 转发 332</转发><评论>评论 325</评论><点赞数>1277</点赞数></item><item><user>芒果捞扒哥</user><内容>
                    #张予曦国潮旗袍# ​张予曦身穿国潮旗袍梳着哪吒头~绝美的旗袍造型，灵性和韵味相互萦绕！爱了爱了 ​                </内容><发布时间>
                        05月10日 17:49
                        </发布时间><来源>微博 weibo.com</来源><收藏>收藏</收藏><转发> 转发 250</转发><评论>评论 268</评论><点赞数>809</点赞数></item><item><user>微博明星</user><内容>
                    #张予曦国潮旗袍#真的太好看了，真的有被惊艳到！小姐姐@张予曦 请做旗袍半永久吧~ ​                </内容><发布时间>
                        05月08日 09:41
                        </发布时间><来源/><收藏>收藏</收藏><转发> 转发 374</转发><评论>评论 383</评论><点赞数>875</点赞数></item><item><user>微博超新星</user><内容>
                    #乔振宇国潮古风装##国潮PLUS挑战赛#先天条件超群的@乔振宇 五官清秀，双眼带电，绿洲晒图潇洒俊逸、气场强大，印象中他的古风装就没有不好磕的 ​                </内容><发布时间>
                        05月01日 20:54
                        </发布时间><来源/><收藏>收藏</收藏><转发> 转发 103</转发><评论>评论 103</评论><点赞数>174</点赞数></item><item><user>圈外人</user><内容>
                    张予曦国潮旗袍，​简直就是女明星苏矜北本人啊 ​                </内容><发布时间>
                        05月20日 11:33
                        </发布时间><来源>微博 weibo.com</来源><收藏>收藏</收藏><转发> 转发 110</转发><评论>评论 150</评论><点赞数>531</点赞数></item><item><user>娱乐圈新鲜事</user><内容>
                    baby鲨我，最新的妆容挑战——国潮龙女妆，你们觉得怎么样？#国潮自拍合伙人# ​                </内容><发布时间>
                        05月18日 13:10
                        </发布时间><来源>微博  weibo.com</来源><收藏>收藏</收藏><转发> 转发 1253</转发><评论>评论 1694</评论><点赞数>4401</点赞数></item><item><user>微博爱豆</user><内容>
                    #乔振宇国潮古风装##国潮PLUS挑战赛#@乔振宇 绿洲晒图，不仅身材保持的很好，年龄感也被冻结了，对比刚出道时竟没有什么改变，怕是真的有时光机吧 ​                </内容><发布时间>
                        05月01日 20:52
                        </发布时间><来源/><收藏>收藏</收藏><转发> 转发 142</转发><评论>评论 137</评论><点赞数>240</点赞数></item><item><user>麦馆</user><内容>
                    最近看很多朋友都在准备野餐，贴心的阿馆我也精挑细选了三款国货老字号美食安利给你们~天气越来越热，怎么能少了雪糕呢，伊利新出的须尽欢的酸奶冰淇淋，一口下去是绵滑的果蔬汁混合着酸奶味，还有7种不同的口味噢，拿出来和小伙伴分享，绝对的有排面呢。再说说上班族每日必须的下午茶，现在正是明前龙 ​  展开全文c                </内容><发布时间>
                        05月11日 19:00
                        </发布时间><来源>微博  weibo.com</来源><收藏>收藏</收藏><转发> 转发 1179</转发><评论>评论 799</评论><点赞数>3177</点赞数></item><item><user>视频主</user><内容>
                    郑恺苗苗官宣结婚，2020.5.21.13.14二人晒出结婚照，苗苗从背后抚摸郑恺的肚子，画风搞怪！之前多次被拍到时不做任何回应，原来是不鸣则已一鸣惊人啊！恭喜恭喜！#国潮# #我的国潮范儿##郑恺苗苗结婚# ​                </内容><发布时间>
                        05月21日 13:36
                        </发布时间><来源>明星娱乐超话</来源><收藏>收藏</收藏><转发> 转发 302</转发><评论>评论 37</评论><点赞数>372</点赞数></item><item><user>瓜组每日速报</user><内容>
                    已经被宋茜的新歌洗脑，都来看看pljj的自拍，新的一周，要和宋教练一起保持微笑哦#宋茜首张同名专辑# #国潮自拍合伙人# ​                </内容><发布时间>
                        05月19日 12:50
                        </发布时间><来源>微博  weibo.com</来源><收藏>收藏</收藏><转发> 转发 635</转发><评论>评论 655</评论><点赞数>2009</点赞数></item><item><user>Holly拾禾一</user><内容>
                    预告预告！今天是充满东方韵味的小哩让我康康你们都喜欢什么国货彩妆呀？#国潮妆有多飒# ​                </内容><发布时间>
                        05月14日 16:40
                        </发布时间><来源/><收藏>收藏</收藏><转发> 转发 40</转发><评论>评论 339</评论><点赞数>1596</点赞数></item><item><user>上汽集团ROEWE荣威</user><内容>
                    【国潮荣威，焕新出发！上汽荣威发布双标战略！】5月10日荣威双标战略正式启动，曾经是亚洲No.1粮仓的民生码头化身“荣威国潮红人馆”，演绎汽车行业最强新国潮。现在跟着荣威君来看看昨晚国潮盛典大回顾吧！O国潮荣威，焕新出发！上汽荣威发布双标战略！ ​                </内容><发布时间>
                        05月11日 18:54
                        </发布时间><来源>专业版微博</来源><收藏>收藏</收藏><转发> 转发 126</转发><评论>评论 210</评论><点赞数>191</点赞数></item><item><user>八鹅吃瓜菌</user><内容>
                    #小朱配琦奔现# 哦买嘎，所有女生，小朱配琦来喽，买它！朱广权李佳琦首次大型网友见面会来咯，将带来 “国潮”直播专场，为国货代言，小朱佩琦冲呀，一起为国货加油，国货棒棒！ ​                </内容><发布时间>
                        05月09日 15:05
                        </发布时间><来源>iPhone XS Max</来源><收藏>收藏</收藏><转发> 转发 389</转发><评论>评论 86</评论><点赞数>411</点赞数></item><item><user>娱乐十二时辰</user><内容>
                    #李玉刚国潮美人范儿# 人比花娇，李玉刚真的很好的演绎了中国风，致敬 ​                </内容><发布时间>
                        05月08日 16:44
                        </发布时间><来源>HUAWEI Mate30 Pro 5G</来源><收藏>收藏</收藏><转发> 转发 138</转发><评论>评论 125</评论><点赞数>223</点赞数></item><item><user>黄俊之</user><内容>
                    这次520换了个伴～#国潮告白日# ​                </内容><发布时间>
                        05月20日 15:43
                        </发布时间><来源/><收藏>收藏</收藏><转发> 转发 119</转发><评论>评论 152</评论><点赞数>384</点赞数></item></讨论></extraction>